LICENSE.txt
MANIFEST.in
README.md
setup.py
cmsplugin_newsplus/__init__.py
cmsplugin_newsplus/__init__.pyc
cmsplugin_newsplus/admin.py
cmsplugin_newsplus/admin.pyc
cmsplugin_newsplus/apps.py
cmsplugin_newsplus/apps.pyc
cmsplugin_newsplus/cms_apps.py
cmsplugin_newsplus/cms_plugins.py
cmsplugin_newsplus/cms_plugins.pyc
cmsplugin_newsplus/feeds.py
cmsplugin_newsplus/feeds.pyc
cmsplugin_newsplus/forms.py
cmsplugin_newsplus/forms.pyc
cmsplugin_newsplus/menu.py
cmsplugin_newsplus/models.py
cmsplugin_newsplus/models.pyc
cmsplugin_newsplus/navigation.py
cmsplugin_newsplus/settings.py
cmsplugin_newsplus/settings.pyc
cmsplugin_newsplus/tests.py
cmsplugin_newsplus/tests.pyc
cmsplugin_newsplus/urls.py
cmsplugin_newsplus/urls.pyc
cmsplugin_newsplus/views.py
cmsplugin_newsplus/views.pyc
cmsplugin_newsplus.egg-info/PKG-INFO
cmsplugin_newsplus.egg-info/SOURCES.txt
cmsplugin_newsplus.egg-info/dependency_links.txt
cmsplugin_newsplus.egg-info/not-zip-safe
cmsplugin_newsplus.egg-info/requires.txt
cmsplugin_newsplus.egg-info/top_level.txt
cmsplugin_newsplus/locale/bg/LC_MESSAGES/django.mo
cmsplugin_newsplus/locale/bg/LC_MESSAGES/django.po
cmsplugin_newsplus/locale/de/LC_MESSAGES/django.mo
cmsplugin_newsplus/locale/de/LC_MESSAGES/django.po
cmsplugin_newsplus/locale/es/LC_MESSAGES/django.mo
cmsplugin_newsplus/locale/es/LC_MESSAGES/django.po
cmsplugin_newsplus/locale/eu/LC_MESSAGES/django.mo
cmsplugin_newsplus/locale/eu/LC_MESSAGES/django.po
cmsplugin_newsplus/locale/ru/LC_MESSAGES/django.mo
cmsplugin_newsplus/locale/ru/LC_MESSAGES/django.po
cmsplugin_newsplus/migrations/0001_initial.py
cmsplugin_newsplus/migrations/0001_initial.pyc
cmsplugin_newsplus/migrations/0002_auto_20150428_1335.py
cmsplugin_newsplus/migrations/0002_auto_20150428_1335.pyc
cmsplugin_newsplus/migrations/__init__.py
cmsplugin_newsplus/migrations/__init__.pyc
cmsplugin_newsplus/south_migrations/0001_initial.py
cmsplugin_newsplus/south_migrations/__init__.py
cmsplugin_newsplus/templates/cmsplugin_newsplus/latest_news.html
cmsplugin_newsplus/templates/cmsplugin_newsplus/news_archive.html
cmsplugin_newsplus/templates/cmsplugin_newsplus/news_archive_day.html
cmsplugin_newsplus/templates/cmsplugin_newsplus/news_archive_month.html
