Metadata-Version: 1.1
Name: cmsplugin-newsplus
Version: 1.1.0
Summary: Simple news plugin for django-cms 3.x
Home-page: https://github.com/nimbis/cmsplugin-newsplus/
Author: Nimbis Services, Inc.
Author-email: devops@nimbisservices.com
License: BSD
Platform: UNKNOWN
Classifier: Development Status :: 4 - Beta
Classifier: Environment :: Web Environment
Classifier: Intended Audience :: Developers
Classifier: License :: OSI Approved :: BSD License
Classifier: Operating System :: OS Independent
Classifier: Programming Language :: Python
Classifier: Framework :: Django
